README.txt
setup.py
erp5flakes/__init__.py
erp5flakes.egg-info/PKG-INFO
erp5flakes.egg-info/SOURCES.txt
erp5flakes.egg-info/dependency_links.txt
erp5flakes.egg-info/entry_points.txt
erp5flakes.egg-info/requires.txt
erp5flakes.egg-info/top_level.txt